cipher_yw3760/__init__.py
cipher_yw3760/cipher_yw3760.py
cipher_yw3760-0.1.0.dist-info/LICENSE
cipher_yw3760-0.1.0.dist-info/WHEEL
cipher_yw3760-0.1.0.dist-info/METADATA
cipher_yw3760-0.1.0.dist-info/RECORD
