Metadata-Version: 2.1
Name: cipher-yw3760
Version: 0.1.0
Summary: an example python package written by Yu Wang for MDS Fall 2021
License: MIT
Author: YU WANG
Requires-Python: >=3.9,<4.0
Classifier: License :: OSI Approved :: MIT License
Classifier: Programming Language :: Python :: 3
Classifier: Programming Language :: Python :: 3.10
Classifier: Programming Language :: Python :: 3.9
Requires-Dist: Sphinx (>=4.2.0,<5.0.0)
